loggia-0.3.1.dist-info/METADATA
loggia-0.3.1.dist-info/WHEEL
loggia-0.3.1.dist-info/licenses/LICENSE
loggia/__init__.py
loggia/_internal/__init__.py
loggia/_internal/bootstrap_logger.py
loggia/_internal/conf.py
loggia/_internal/env_parsers.py
loggia/_internal/loguru_stuff.py
loggia/_internal/presets.py
loggia/_version.py
loggia/auto.py
loggia/base_preset.py
loggia/conf.py
loggia/constants.py
loggia/filters/__init__.py
loggia/filters/extra_allow.py
loggia/logger.py
loggia/loguru_sink.py
loggia/presets/__init__.py
loggia/presets/datadog_normalisation.py
loggia/presets/dev.py
loggia/presets/gunicorn.py
loggia/presets/hypercorn.py
loggia/presets/null_preset.py
loggia/presets/prod.py
loggia/py.typed
loggia/stdlib_formatters/__init__.py
loggia/stdlib_formatters/json_formatter.py
loggia/stdlib_formatters/pretty_formatter.py
loggia/structlog_utils/__init__.py
loggia/structlog_utils/gunicorn_logger.py
loggia/structlog_utils/hypercorn_logger.py
loggia/types.py
loggia/utils/__init__.py
loggia/utils/colorsutils.py
loggia/utils/dictutils.py
loggia/utils/envutils.py
loggia/utils/loaderutils.py
loggia/utils/logrecordutils.py
loggia/utils/strutils.py
loggia-0.3.1.dist-info/RECORD
