Metadata-Version: 2.1
Name: loggia
Version: 0.3.1
Summary: A convenient logging configuration manager for Python's standard logging library and Loguru.
Author-Email: Gabriel Dugny <gabriel.dugny@manomano.com>, Elie Bleton <elie.bleton@manomano.com>, Jonathan Gallon <jonathan.gallon@manomano.com>
License: Copyright (c) 2021 - 2024 ManoMano Colibri SAS
Classifier: Development Status :: 3 - Alpha
Classifier: Intended Audience :: Developers
Classifier: License :: OSI Approved :: ISC License (ISCL)
Classifier: Programming Language :: Python :: 3
Classifier: Programming Language :: Python :: 3 :: Only
Classifier: Programming Language :: Python :: 3.9
Classifier: Programming Language :: Python :: 3.10
Classifier: Programming Language :: Python :: 3.11
Classifier: Programming Language :: Python :: 3.12
Classifier: Typing :: Typed
Classifier: Topic :: Software Development :: Libraries :: Python Modules
Classifier: Topic :: System :: Logging
Classifier: Topic :: Utilities
Classifier: Operating System :: OS Independent
Classifier: Environment :: Console
Classifier: Environment :: Web Environment
Project-URL: Repository, https://github.com/ManoManoTech/loggia
Project-URL: Documentation, https://manomanotech.github.io/loggia/latest/
Project-URL: Changelog, https://manomanotech.github.io/loggia/latest/CHANGELOG/
Requires-Python: >=3.9
Requires-Dist: python-json-logger>=2.0.7
Requires-Dist: typing-extensions>=4.7.1; python_version < "3.10"
Requires-Dist: loguru>=0.7.0; extra == "loguru"
Requires-Dist: rich>=13.3.4; extra == "rich"
Requires-Dist: ddtrace>=1.18.0; extra == "ddtrace"
Provides-Extra: loguru
Provides-Extra: rich
Provides-Extra: ddtrace
